cloudcoil/models/kubernetes/__init__.py
cloudcoil/models/kubernetes/py.typed
cloudcoil/models/kubernetes/admissionregistration/__init__.py
cloudcoil/models/kubernetes/admissionregistration/v1.py
cloudcoil/models/kubernetes/admissionregistration/v1alpha1.py
cloudcoil/models/kubernetes/admissionregistration/v1beta1.py
cloudcoil/models/kubernetes/apiextensions/__init__.py
cloudcoil/models/kubernetes/apiextensions/v1.py
cloudcoil/models/kubernetes/apiregistration/__init__.py
cloudcoil/models/kubernetes/apiregistration/v1.py
cloudcoil/models/kubernetes/apiserverinternal/__init__.py
cloudcoil/models/kubernetes/apiserverinternal/v1alpha1.py
cloudcoil/models/kubernetes/apps/__init__.py
cloudcoil/models/kubernetes/apps/v1.py
cloudcoil/models/kubernetes/authentication/__init__.py
cloudcoil/models/kubernetes/authentication/v1.py
cloudcoil/models/kubernetes/authentication/v1beta1.py
cloudcoil/models/kubernetes/authorization/__init__.py
cloudcoil/models/kubernetes/authorization/v1.py
cloudcoil/models/kubernetes/autoscaling/__init__.py
cloudcoil/models/kubernetes/autoscaling/v1.py
cloudcoil/models/kubernetes/autoscaling/v2.py
cloudcoil/models/kubernetes/batch/__init__.py
cloudcoil/models/kubernetes/batch/v1.py
cloudcoil/models/kubernetes/certificates/__init__.py
cloudcoil/models/kubernetes/certificates/v1.py
cloudcoil/models/kubernetes/certificates/v1alpha1.py
cloudcoil/models/kubernetes/coordination/__init__.py
cloudcoil/models/kubernetes/coordination/v1.py
cloudcoil/models/kubernetes/coordination/v1alpha2.py
cloudcoil/models/kubernetes/core/__init__.py
cloudcoil/models/kubernetes/core/v1.py
cloudcoil/models/kubernetes/discovery/__init__.py
cloudcoil/models/kubernetes/discovery/v1.py
cloudcoil/models/kubernetes/events/__init__.py
cloudcoil/models/kubernetes/events/v1.py
cloudcoil/models/kubernetes/flowcontrol/__init__.py
cloudcoil/models/kubernetes/flowcontrol/v1.py
cloudcoil/models/kubernetes/networking/__init__.py
cloudcoil/models/kubernetes/networking/v1.py
cloudcoil_models_kubernetes-1.32.1.2.dist-info/METADATA
cloudcoil_models_kubernetes-1.32.1.2.dist-info/WHEEL
cloudcoil_models_kubernetes-1.32.1.2.dist-info/licenses/LICENSE
cloudcoil_models_kubernetes-1.32.1.2.dist-info/RECORD
